splitnstitch/__init__.py
splitnstitch/__main__.py
splitnstitch/splitnstitch.py
splitnstitch-0.1.0.dist-info/licenses/LICENSE
splitnstitch-0.1.0.dist-info/METADATA
splitnstitch-0.1.0.dist-info/WHEEL
splitnstitch-0.1.0.dist-info/entry_points.txt
splitnstitch-0.1.0.dist-info/top_level.txt
splitnstitch-0.1.0.dist-info/RECORD
