Metadata-Version: 2.4
Name: splitnstitch
Version: 0.1.0
Summary: CLI tool for splitting and merging table files (safe export / import merge).
Author: espehon
License: MIT License
Classifier: License :: OSI Approved :: MIT License
Classifier: Programming Language :: Python
Classifier: Programming Language :: Python :: 3
Classifier: Programming Language :: Python :: 3 :: Only
Classifier: Programming Language :: Python :: 3.8
Classifier: Programming Language :: Python :: 3.9
Classifier: Programming Language :: Python :: 3.10
Classifier: Programming Language :: Python :: 3.11
Classifier: Operating System :: OS Independent
Requires-Python: >=3.8
License-File: LICENSE
Requires-Dist: pandas==3.0.0
Requires-Dist: questionary==2.1.1
Requires-Dist: halo==0.0.31
Dynamic: license-file
